README.txt
setup.py
esbench/__init__.py
esbench/analyze.py
esbench/api.py
esbench/bench.py
esbench/client.py
esbench/config.json
esbench/data.py
esbench.egg-info/PKG-INFO
esbench.egg-info/SOURCES.txt
esbench.egg-info/dependency_links.txt
esbench.egg-info/entry_points.txt
esbench.egg-info/requires.txt
esbench.egg-info/top_level.txt
esbench/test/__init__.py
esbench/test/test_analyze.py
esbench/test/test_api.py
esbench/test/test_bench.py
esbench/test/test_client.py
esbench/test/test_data.py
esbench/test/units.py