Metadata-Version: 1.1
Name: esbench
Version: 0.1.0
Summary: Elasticsearch performance benchmark tool
Home-page: https://github.com/mkocikowski/esbench
Author: Mik Kocikowski
Author-email: mkocikowski@gmail.com
License: MIT
Platform: UNKNOWN
Classifier: Development Status :: 3 - Alpha
Classifier: Environment :: Console
Classifier: Intended Audience :: Developers
Classifier: License :: OSI Approved :: MIT License
Classifier: Natural Language :: English
Classifier: Operating System :: POSIX
Classifier: Topic :: System :: Benchmark
Classifier: Topic :: Internet :: WWW/HTTP :: Indexing/Search
Classifier: Topic :: Utilities
